odoo/addons/website_sale_address_format/README.rst
odoo/addons/website_sale_address_format/__init__.py
odoo/addons/website_sale_address_format/__manifest__.py
odoo/addons/website_sale_address_format/controllers/__init__.py
odoo/addons/website_sale_address_format/controllers/main.py
odoo/addons/website_sale_address_format/i18n/es.po
odoo/addons/website_sale_address_format/i18n/website_sale_address_format.pot
odoo/addons/website_sale_address_format/models/__init__.py
odoo/addons/website_sale_address_format/models/res_country.py
odoo/addons/website_sale_address_format/readme/CONFIGURE.rst
odoo/addons/website_sale_address_format/readme/CONTRIBUTORS.rst
odoo/addons/website_sale_address_format/readme/DESCRIPTION.rst
odoo/addons/website_sale_address_format/static/description/icon.png
odoo/addons/website_sale_address_format/static/description/index.html
odoo/addons/website_sale_address_format/static/src/js/website_sale_address_format.js
odoo/addons/website_sale_address_format/tests/__init__.py
odoo/addons/website_sale_address_format/tests/test_website_sale_address_format.py
odoo/addons/website_sale_address_format/views/res_country_views.xml
odoo_addon_website_sale_address_format-15.0.1.0.0.6.dist-info/METADATA
odoo_addon_website_sale_address_format-15.0.1.0.0.6.dist-info/WHEEL
odoo_addon_website_sale_address_format-15.0.1.0.0.6.dist-info/top_level.txt
odoo_addon_website_sale_address_format-15.0.1.0.0.6.dist-info/RECORD
